covid_india/__init__.py
covid_india/states.py
covid_india-1.1.4.dist-info/LICENSE
covid_india-1.1.4.dist-info/METADATA
covid_india-1.1.4.dist-info/WHEEL
covid_india-1.1.4.dist-info/top_level.txt
covid_india-1.1.4.dist-info/RECORD
