Metadata-Version: 2.1
Name: covid-india
Version: 1.1.4
Summary: A package to provide information regarding COVID-19 cases in India.
Home-page: https://github.com/debdutgoswami/covid-19-India
Author: Debdut Goswami
Author-email: debdutgoswami@gmail.com
License: UNKNOWN
Download-URL: https://github.com/debdutgoswami/covid-19-India/archive/v_1.1.4.tar.gz
Platform: UNKNOWN
Classifier: Programming Language :: Python :: 3
Classifier: License :: OSI Approved :: MIT License
Classifier: Operating System :: OS Independent
Requires-Python: >=3
Requires-Dist: requests
Requires-Dist: pandas
Requires-Dist: lxml
